setup.py
fcc_distributions/Binomialdistribution.py
fcc_distributions/Gaussiandistribution.py
fcc_distributions/Generaldistribution.py
fcc_distributions/__init__.py
fcc_distributions.egg-info/PKG-INFO
fcc_distributions.egg-info/SOURCES.txt
fcc_distributions.egg-info/dependency_links.txt
fcc_distributions.egg-info/not-zip-safe
fcc_distributions.egg-info/top_level.txt