Metadata-Version: 1.0
Name: fcc-distributions
Version: 0.1
Summary: Gaussian  and binomial distributions
Home-page: UNKNOWN
Author: Francisco Chavez
Author-email: something@else.com
License: UNKNOWN
Platform: UNKNOWN
